setup.py
PySet2/__init__.py
PySet2/img_qc_rc.py
PySet2/sample.py
PySet2/settingsMgr.py
PySet2/uic.py
PySet2.egg-info/PKG-INFO
PySet2.egg-info/SOURCES.txt
PySet2.egg-info/dependency_links.txt
PySet2.egg-info/top_level.txt