Metadata-Version: 2.1
Name: PySet2
Version: 0.0.1
Summary: PySide2设置工具/Pyside2 setup tool
Home-page: https://yangguang-gongzuoshi.top/wry/
Author: Ruoyu Wang
Author-email: wry2022@outlook.com
License: MIT License
Platform: UNKNOWN
Requires: PyQt5
